{
    "@context": "http://iiif.io/api/presentation/3/context.json",
    "id": "https://tu-delft-heritage.github.io/iiif-annotations/supplementing/txf-18197/403.json",
    "type": "AnnotationPage",
    "items": [
        {
            "id": "https://tu-delft-heritage.github.io/iiif-annotations/403/annotation/0",
            "type": "Annotation",
            "motivation": "supplementing",
            "body": {
                "type": "TextualBody",
                "format": "text/plain",
                "value": "ires"
            },
            "target": "https://dlc.services/iiif-img/7/6/e3f53862-12e5-4f01-9bdb-a53f591e1ebd/canvas/c/404#xywh=85,2747,13,94"
        },
        {
            "id": "https://tu-delft-heritage.github.io/iiif-annotations/403/annotation/1",
            "type": "Annotation",
            "motivation": "supplementing",
            "body": {
                "type": "TextualBody",
                "format": "text/plain",
                "value": "pd"
            },
            "target": "https://dlc.services/iiif-img/7/6/e3f53862-12e5-4f01-9bdb-a53f591e1ebd/canvas/c/404#xywh=60,2649,8,29"
        },
        {
            "id": "https://tu-delft-heritage.github.io/iiif-annotations/403/annotation/2",
            "type": "Annotation",
            "motivation": "supplementing",
            "body": {
                "type": "TextualBody",
                "format": "text/plain",
                "value": "nin,"
            },
            "target": "https://dlc.services/iiif-img/7/6/e3f53862-12e5-4f01-9bdb-a53f591e1ebd/canvas/c/404#xywh=61,2691,7,120"
        },
        {
            "id": "https://tu-delft-heritage.github.io/iiif-annotations/403/annotation/3",
            "type": "Annotation",
            "motivation": "supplementing",
            "body": {
                "type": "TextualBody",
                "format": "text/plain",
                "value": "2E"
            },
            "target": "https://dlc.services/iiif-img/7/6/e3f53862-12e5-4f01-9bdb-a53f591e1ebd/canvas/c/404#xywh=60,2835,13,48"
        },
        {
            "id": "https://tu-delft-heritage.github.io/iiif-annotations/403/annotation/4",
            "type": "Annotation",
            "motivation": "supplementing",
            "body": {
                "type": "TextualBody",
                "format": "text/plain",
                "value": "DE"
            },
            "target": "https://dlc.services/iiif-img/7/6/e3f53862-12e5-4f01-9bdb-a53f591e1ebd/canvas/c/404#xywh=52,2948,29,23"
        },
        {
            "id": "https://tu-delft-heritage.github.io/iiif-annotations/403/annotation/5",
            "type": "Annotation",
            "motivation": "supplementing",
            "body": {
                "type": "TextualBody",
                "format": "text/plain",
                "value": "reve"
            },
            "target": "https://dlc.services/iiif-img/7/6/e3f53862-12e5-4f01-9bdb-a53f591e1ebd/canvas/c/404#xywh=61,2963,16,116"
        },
        {
            "id": "https://tu-delft-heritage.github.io/iiif-annotations/403/annotation/6",
            "type": "Annotation",
            "motivation": "supplementing",
            "body": {
                "type": "TextualBody",
                "format": "text/plain",
                "value": "nd"
            },
            "target": "https://dlc.services/iiif-img/7/6/e3f53862-12e5-4f01-9bdb-a53f591e1ebd/canvas/c/404#xywh=67,3080,7,40"
        },
        {
            "id": "https://tu-delft-heritage.github.io/iiif-annotations/403/annotation/7",
            "type": "Annotation",
            "motivation": "supplementing",
            "body": {
                "type": "TextualBody",
                "format": "text/plain",
                "value": "EE"
            },
            "target": "https://dlc.services/iiif-img/7/6/e3f53862-12e5-4f01-9bdb-a53f591e1ebd/canvas/c/404#xywh=44,2740,8,31"
        },
        {
            "id": "https://tu-delft-heritage.github.io/iiif-annotations/403/annotation/8",
            "type": "Annotation",
            "motivation": "supplementing",
            "body": {
                "type": "TextualBody",
                "format": "text/plain",
                "value": "EE"
            },
            "target": "https://dlc.services/iiif-img/7/6/e3f53862-12e5-4f01-9bdb-a53f591e1ebd/canvas/c/404#xywh=45,2779,12,169"
        },
        {
            "id": "https://tu-delft-heritage.github.io/iiif-annotations/403/annotation/9",
            "type": "Annotation",
            "motivation": "supplementing",
            "body": {
                "type": "TextualBody",
                "format": "text/plain",
                "value": "SE"
            },
            "target": "https://dlc.services/iiif-img/7/6/e3f53862-12e5-4f01-9bdb-a53f591e1ebd/canvas/c/404#xywh=40,2936,28,17"
        },
        {
            "id": "https://tu-delft-heritage.github.io/iiif-annotations/403/annotation/10",
            "type": "Annotation",
            "motivation": "supplementing",
            "body": {
                "type": "TextualBody",
                "format": "text/plain",
                "value": "at"
            },
            "target": "https://dlc.services/iiif-img/7/6/e3f53862-12e5-4f01-9bdb-a53f591e1ebd/canvas/c/404#xywh=48,2961,9,101"
        },
        {
            "id": "https://tu-delft-heritage.github.io/iiif-annotations/403/annotation/11",
            "type": "Annotation",
            "motivation": "supplementing",
            "body": {
                "type": "TextualBody",
                "format": "text/plain",
                "value": "jn"
            },
            "target": "https://dlc.services/iiif-img/7/6/e3f53862-12e5-4f01-9bdb-a53f591e1ebd/canvas/c/404#xywh=49,3079,10,90"
        },
        {
            "id": "https://tu-delft-heritage.github.io/iiif-annotations/403/annotation/12",
            "type": "Annotation",
            "motivation": "supplementing",
            "body": {
                "type": "TextualBody",
                "format": "text/plain",
                "value": "|"
            },
            "target": "https://dlc.services/iiif-img/7/6/e3f53862-12e5-4f01-9bdb-a53f591e1ebd/canvas/c/404#xywh=755,3813,27,3"
        },
        {
            "id": "https://tu-delft-heritage.github.io/iiif-annotations/403/annotation/13",
            "type": "Annotation",
            "motivation": "supplementing",
            "body": {
                "type": "TextualBody",
                "format": "text/plain",
                "value": "|"
            },
            "target": "https://dlc.services/iiif-img/7/6/e3f53862-12e5-4f01-9bdb-a53f591e1ebd/canvas/c/404#xywh=718,3812,14,3"
        },
        {
            "id": "https://tu-delft-heritage.github.io/iiif-annotations/403/annotation/14",
            "type": "Annotation",
            "motivation": "supplementing",
            "body": {
                "type": "TextualBody",
                "format": "text/plain",
                "value": "|"
            },
            "target": "https://dlc.services/iiif-img/7/6/e3f53862-12e5-4f01-9bdb-a53f591e1ebd/canvas/c/404#xywh=696,3811,19,4"
        },
        {
            "id": "https://tu-delft-heritage.github.io/iiif-annotations/403/annotation/15",
            "type": "Annotation",
            "motivation": "supplementing",
            "body": {
                "type": "TextualBody",
                "format": "text/plain",
                "value": "|"
            },
            "target": "https://dlc.services/iiif-img/7/6/e3f53862-12e5-4f01-9bdb-a53f591e1ebd/canvas/c/404#xywh=655,3809,40,6"
        }
    ]
}