{
    "@context": "http://iiif.io/api/presentation/3/context.json",
    "id": "https://tu-delft-heritage.github.io/iiif-annotations/supplementing/txf-18197/426.json",
    "type": "AnnotationPage",
    "items": [
        {
            "id": "https://tu-delft-heritage.github.io/iiif-annotations/426/annotation/0",
            "type": "Annotation",
            "motivation": "supplementing",
            "body": {
                "type": "TextualBody",
                "format": "text/plain",
                "value": "PLAAT"
            },
            "target": "https://dlc.services/iiif-img/7/6/76e1ce36-7b6e-4451-8ab5-3eb72db90856/canvas/c/427#xywh=2406,191,154,30"
        },
        {
            "id": "https://tu-delft-heritage.github.io/iiif-annotations/426/annotation/1",
            "type": "Annotation",
            "motivation": "supplementing",
            "body": {
                "type": "TextualBody",
                "format": "text/plain",
                "value": "Xf."
            },
            "target": "https://dlc.services/iiif-img/7/6/76e1ce36-7b6e-4451-8ab5-3eb72db90856/canvas/c/427#xywh=2584,192,65,40"
        },
        {
            "id": "https://tu-delft-heritage.github.io/iiif-annotations/426/annotation/2",
            "type": "Annotation",
            "motivation": "supplementing",
            "body": {
                "type": "TextualBody",
                "format": "text/plain",
                "value": "L"
            },
            "target": "https://dlc.services/iiif-img/7/6/76e1ce36-7b6e-4451-8ab5-3eb72db90856/canvas/c/427#xywh=2267,3034,19,35"
        },
        {
            "id": "https://tu-delft-heritage.github.io/iiif-annotations/426/annotation/3",
            "type": "Annotation",
            "motivation": "supplementing",
            "body": {
                "type": "TextualBody",
                "format": "text/plain",
                "value": "W."
            },
            "target": "https://dlc.services/iiif-img/7/6/76e1ce36-7b6e-4451-8ab5-3eb72db90856/canvas/c/427#xywh=2198,3033,53,35"
        },
        {
            "id": "https://tu-delft-heritage.github.io/iiif-annotations/426/annotation/4",
            "type": "Annotation",
            "motivation": "supplementing",
            "body": {
                "type": "TextualBody",
                "format": "text/plain",
                "value": "r"
            },
            "target": "https://dlc.services/iiif-img/7/6/76e1ce36-7b6e-4451-8ab5-3eb72db90856/canvas/c/427#xywh=2215,3093,17,20"
        },
        {
            "id": "https://tu-delft-heritage.github.io/iiif-annotations/426/annotation/5",
            "type": "Annotation",
            "motivation": "supplementing",
            "body": {
                "type": "TextualBody",
                "format": "text/plain",
                "value": "EPAST"
            },
            "target": "https://dlc.services/iiif-img/7/6/76e1ce36-7b6e-4451-8ab5-3eb72db90856/canvas/c/427#xywh=2111,3092,100,21"
        },
        {
            "id": "https://tu-delft-heritage.github.io/iiif-annotations/426/annotation/6",
            "type": "Annotation",
            "motivation": "supplementing",
            "body": {
                "type": "TextualBody",
                "format": "text/plain",
                "value": ","
            },
            "target": "https://dlc.services/iiif-img/7/6/76e1ce36-7b6e-4451-8ab5-3eb72db90856/canvas/c/427#xywh=2177,3062,6,11"
        },
        {
            "id": "https://tu-delft-heritage.github.io/iiif-annotations/426/annotation/7",
            "type": "Annotation",
            "motivation": "supplementing",
            "body": {
                "type": "TextualBody",
                "format": "text/plain",
                "value": "SRECHT"
            },
            "target": "https://dlc.services/iiif-img/7/6/76e1ce36-7b6e-4451-8ab5-3eb72db90856/canvas/c/427#xywh=2056,1726,123,21"
        },
        {
            "id": "https://tu-delft-heritage.github.io/iiif-annotations/426/annotation/8",
            "type": "Annotation",
            "motivation": "supplementing",
            "body": {
                "type": "TextualBody",
                "format": "text/plain",
                "value": "EN"
            },
            "target": "https://dlc.services/iiif-img/7/6/76e1ce36-7b6e-4451-8ab5-3eb72db90856/canvas/c/427#xywh=2196,1727,40,21"
        },
        {
            "id": "https://tu-delft-heritage.github.io/iiif-annotations/426/annotation/9",
            "type": "Annotation",
            "motivation": "supplementing",
            "body": {
                "type": "TextualBody",
                "format": "text/plain",
                "value": "DE"
            },
            "target": "https://dlc.services/iiif-img/7/6/76e1ce36-7b6e-4451-8ab5-3eb72db90856/canvas/c/427#xywh=2252,1727,41,21"
        },
        {
            "id": "https://tu-delft-heritage.github.io/iiif-annotations/426/annotation/10",
            "type": "Annotation",
            "motivation": "supplementing",
            "body": {
                "type": "TextualBody",
                "format": "text/plain",
                "value": "{e)"
            },
            "target": "https://dlc.services/iiif-img/7/6/76e1ce36-7b6e-4451-8ab5-3eb72db90856/canvas/c/427#xywh=2255,1631,38,40"
        },
        {
            "id": "https://tu-delft-heritage.github.io/iiif-annotations/426/annotation/11",
            "type": "Annotation",
            "motivation": "supplementing",
            "body": {
                "type": "TextualBody",
                "format": "text/plain",
                "value": "\u00a3"
            },
            "target": "https://dlc.services/iiif-img/7/6/76e1ce36-7b6e-4451-8ab5-3eb72db90856/canvas/c/427#xywh=2204,1631,45,35"
        },
        {
            "id": "https://tu-delft-heritage.github.io/iiif-annotations/426/annotation/12",
            "type": "Annotation",
            "motivation": "supplementing",
            "body": {
                "type": "TextualBody",
                "format": "text/plain",
                "value": "fg"
            },
            "target": "https://dlc.services/iiif-img/7/6/76e1ce36-7b6e-4451-8ab5-3eb72db90856/canvas/c/427#xywh=2165,1631,33,34"
        },
        {
            "id": "https://tu-delft-heritage.github.io/iiif-annotations/426/annotation/13",
            "type": "Annotation",
            "motivation": "supplementing",
            "body": {
                "type": "TextualBody",
                "format": "text/plain",
                "value": "ZL"
            },
            "target": "https://dlc.services/iiif-img/7/6/76e1ce36-7b6e-4451-8ab5-3eb72db90856/canvas/c/427#xywh=2126,1630,33,35"
        },
        {
            "id": "https://tu-delft-heritage.github.io/iiif-annotations/426/annotation/14",
            "type": "Annotation",
            "motivation": "supplementing",
            "body": {
                "type": "TextualBody",
                "format": "text/plain",
                "value": "En"
            },
            "target": "https://dlc.services/iiif-img/7/6/76e1ce36-7b6e-4451-8ab5-3eb72db90856/canvas/c/427#xywh=2089,1629,32,35"
        },
        {
            "id": "https://tu-delft-heritage.github.io/iiif-annotations/426/annotation/15",
            "type": "Annotation",
            "motivation": "supplementing",
            "body": {
                "type": "TextualBody",
                "format": "text/plain",
                "value": "zal"
            },
            "target": "https://dlc.services/iiif-img/7/6/76e1ce36-7b6e-4451-8ab5-3eb72db90856/canvas/c/427#xywh=2054,1629,29,36"
        },
        {
            "id": "https://tu-delft-heritage.github.io/iiif-annotations/426/annotation/16",
            "type": "Annotation",
            "motivation": "supplementing",
            "body": {
                "type": "TextualBody",
                "format": "text/plain",
                "value": "IL"
            },
            "target": "https://dlc.services/iiif-img/7/6/76e1ce36-7b6e-4451-8ab5-3eb72db90856/canvas/c/427#xywh=2018,1629,30,36"
        },
        {
            "id": "https://tu-delft-heritage.github.io/iiif-annotations/426/annotation/17",
            "type": "Annotation",
            "motivation": "supplementing",
            "body": {
                "type": "TextualBody",
                "format": "text/plain",
                "value": "NS"
            },
            "target": "https://dlc.services/iiif-img/7/6/76e1ce36-7b6e-4451-8ab5-3eb72db90856/canvas/c/427#xywh=1982,1629,32,35"
        },
        {
            "id": "https://tu-delft-heritage.github.io/iiif-annotations/426/annotation/18",
            "type": "Annotation",
            "motivation": "supplementing",
            "body": {
                "type": "TextualBody",
                "format": "text/plain",
                "value": "LJ"
            },
            "target": "https://dlc.services/iiif-img/7/6/76e1ce36-7b6e-4451-8ab5-3eb72db90856/canvas/c/427#xywh=1946,1627,30,36"
        },
        {
            "id": "https://tu-delft-heritage.github.io/iiif-annotations/426/annotation/19",
            "type": "Annotation",
            "motivation": "supplementing",
            "body": {
                "type": "TextualBody",
                "format": "text/plain",
                "value": "d5"
            },
            "target": "https://dlc.services/iiif-img/7/6/76e1ce36-7b6e-4451-8ab5-3eb72db90856/canvas/c/427#xywh=1911,1628,29,35"
        },
        {
            "id": "https://tu-delft-heritage.github.io/iiif-annotations/426/annotation/20",
            "type": "Annotation",
            "motivation": "supplementing",
            "body": {
                "type": "TextualBody",
                "format": "text/plain",
                "value": "E"
            },
            "target": "https://dlc.services/iiif-img/7/6/76e1ce36-7b6e-4451-8ab5-3eb72db90856/canvas/c/427#xywh=1833,1627,44,35"
        },
        {
            "id": "https://tu-delft-heritage.github.io/iiif-annotations/426/annotation/21",
            "type": "Annotation",
            "motivation": "supplementing",
            "body": {
                "type": "TextualBody",
                "format": "text/plain",
                "value": "g\u00fa"
            },
            "target": "https://dlc.services/iiif-img/7/6/76e1ce36-7b6e-4451-8ab5-3eb72db90856/canvas/c/427#xywh=1742,1626,58,36"
        },
        {
            "id": "https://tu-delft-heritage.github.io/iiif-annotations/426/annotation/22",
            "type": "Annotation",
            "motivation": "supplementing",
            "body": {
                "type": "TextualBody",
                "format": "text/plain",
                "value": "ze"
            },
            "target": "https://dlc.services/iiif-img/7/6/76e1ce36-7b6e-4451-8ab5-3eb72db90856/canvas/c/427#xywh=1701,1623,40,37"
        },
        {
            "id": "https://tu-delft-heritage.github.io/iiif-annotations/426/annotation/23",
            "type": "Annotation",
            "motivation": "supplementing",
            "body": {
                "type": "TextualBody",
                "format": "text/plain",
                "value": "Z"
            },
            "target": "https://dlc.services/iiif-img/7/6/76e1ce36-7b6e-4451-8ab5-3eb72db90856/canvas/c/427#xywh=1654,1626,44,35"
        },
        {
            "id": "https://tu-delft-heritage.github.io/iiif-annotations/426/annotation/24",
            "type": "Annotation",
            "motivation": "supplementing",
            "body": {
                "type": "TextualBody",
                "format": "text/plain",
                "value": "HOOGLEERAAR"
            },
            "target": "https://dlc.services/iiif-img/7/6/76e1ce36-7b6e-4451-8ab5-3eb72db90856/canvas/c/427#xywh=1653,1686,243,22"
        },
        {
            "id": "https://tu-delft-heritage.github.io/iiif-annotations/426/annotation/25",
            "type": "Annotation",
            "motivation": "supplementing",
            "body": {
                "type": "TextualBody",
                "format": "text/plain",
                "value": "IN"
            },
            "target": "https://dlc.services/iiif-img/7/6/76e1ce36-7b6e-4451-8ab5-3eb72db90856/canvas/c/427#xywh=1917,1688,29,20"
        },
        {
            "id": "https://tu-delft-heritage.github.io/iiif-annotations/426/annotation/26",
            "type": "Annotation",
            "motivation": "supplementing",
            "body": {
                "type": "TextualBody",
                "format": "text/plain",
                "value": "HET"
            },
            "target": "https://dlc.services/iiif-img/7/6/76e1ce36-7b6e-4451-8ab5-3eb72db90856/canvas/c/427#xywh=1963,1687,61,22"
        },
        {
            "id": "https://tu-delft-heritage.github.io/iiif-annotations/426/annotation/27",
            "type": "Annotation",
            "motivation": "supplementing",
            "body": {
                "type": "TextualBody",
                "format": "text/plain",
                "value": "STAATS-,"
            },
            "target": "https://dlc.services/iiif-img/7/6/76e1ce36-7b6e-4451-8ab5-3eb72db90856/canvas/c/427#xywh=2040,1689,143,25"
        },
        {
            "id": "https://tu-delft-heritage.github.io/iiif-annotations/426/annotation/28",
            "type": "Annotation",
            "motivation": "supplementing",
            "body": {
                "type": "TextualBody",
                "format": "text/plain",
                "value": "ADMI"
            },
            "target": "https://dlc.services/iiif-img/7/6/76e1ce36-7b6e-4451-8ab5-3eb72db90856/canvas/c/427#xywh=2200,1691,94,20"
        },
        {
            "id": "https://tu-delft-heritage.github.io/iiif-annotations/426/annotation/29",
            "type": "Annotation",
            "motivation": "supplementing",
            "body": {
                "type": "TextualBody",
                "format": "text/plain",
                "value": "NISTRATIEF-"
            },
            "target": "https://dlc.services/iiif-img/7/6/76e1ce36-7b6e-4451-8ab5-3eb72db90856/canvas/c/427#xywh=1652,1722,200,22"
        },
        {
            "id": "https://tu-delft-heritage.github.io/iiif-annotations/426/annotation/30",
            "type": "Annotation",
            "motivation": "supplementing",
            "body": {
                "type": "TextualBody",
                "format": "text/plain",
                "value": "EN"
            },
            "target": "https://dlc.services/iiif-img/7/6/76e1ce36-7b6e-4451-8ab5-3eb72db90856/canvas/c/427#xywh=1868,1724,40,20"
        },
        {
            "id": "https://tu-delft-heritage.github.io/iiif-annotations/426/annotation/31",
            "type": "Annotation",
            "motivation": "supplementing",
            "body": {
                "type": "TextualBody",
                "format": "text/plain",
                "value": "HANDEL"
            },
            "target": "https://dlc.services/iiif-img/7/6/76e1ce36-7b6e-4451-8ab5-3eb72db90856/canvas/c/427#xywh=1924,1725,129,21"
        },
        {
            "id": "https://tu-delft-heritage.github.io/iiif-annotations/426/annotation/32",
            "type": "Annotation",
            "motivation": "supplementing",
            "body": {
                "type": "TextualBody",
                "format": "text/plain",
                "value": "STAATHUISHOUDKUNDE,"
            },
            "target": "https://dlc.services/iiif-img/7/6/76e1ce36-7b6e-4451-8ab5-3eb72db90856/canvas/c/427#xywh=1651,1758,390,24"
        },
        {
            "id": "https://tu-delft-heritage.github.io/iiif-annotations/426/annotation/33",
            "type": "Annotation",
            "motivation": "supplementing",
            "body": {
                "type": "TextualBody",
                "format": "text/plain",
                "value": "SECRETARIS"
            },
            "target": "https://dlc.services/iiif-img/7/6/76e1ce36-7b6e-4451-8ab5-3eb72db90856/canvas/c/427#xywh=1651,1794,198,23"
        },
        {
            "id": "https://tu-delft-heritage.github.io/iiif-annotations/426/annotation/34",
            "type": "Annotation",
            "motivation": "supplementing",
            "body": {
                "type": "TextualBody",
                "format": "text/plain",
                "value": "VAN"
            },
            "target": "https://dlc.services/iiif-img/7/6/76e1ce36-7b6e-4451-8ab5-3eb72db90856/canvas/c/427#xywh=1872,1796,65,21"
        },
        {
            "id": "https://tu-delft-heritage.github.io/iiif-annotations/426/annotation/35",
            "type": "Annotation",
            "motivation": "supplementing",
            "body": {
                "type": "TextualBody",
                "format": "text/plain",
                "value": "DEN"
            },
            "target": "https://dlc.services/iiif-img/7/6/76e1ce36-7b6e-4451-8ab5-3eb72db90856/canvas/c/427#xywh=1960,1797,64,21"
        },
        {
            "id": "https://tu-delft-heritage.github.io/iiif-annotations/426/annotation/36",
            "type": "Annotation",
            "motivation": "supplementing",
            "body": {
                "type": "TextualBody",
                "format": "text/plain",
                "value": "SENAAT."
            },
            "target": "https://dlc.services/iiif-img/7/6/76e1ce36-7b6e-4451-8ab5-3eb72db90856/canvas/c/427#xywh=2046,1797,134,22"
        },
        {
            "id": "https://tu-delft-heritage.github.io/iiif-annotations/426/annotation/37",
            "type": "Annotation",
            "motivation": "supplementing",
            "body": {
                "type": "TextualBody",
                "format": "text/plain",
                "value": "D=."
            },
            "target": "https://dlc.services/iiif-img/7/6/76e1ce36-7b6e-4451-8ab5-3eb72db90856/canvas/c/427#xywh=1646,3026,67,38"
        },
        {
            "id": "https://tu-delft-heritage.github.io/iiif-annotations/426/annotation/38",
            "type": "Annotation",
            "motivation": "supplementing",
            "body": {
                "type": "TextualBody",
                "format": "text/plain",
                "value": "C."
            },
            "target": "https://dlc.services/iiif-img/7/6/76e1ce36-7b6e-4451-8ab5-3eb72db90856/canvas/c/427#xywh=1729,3029,40,36"
        },
        {
            "id": "https://tu-delft-heritage.github.io/iiif-annotations/426/annotation/39",
            "type": "Annotation",
            "motivation": "supplementing",
            "body": {
                "type": "TextualBody",
                "format": "text/plain",
                "value": "A-SCHELTEMA"
            },
            "target": "https://dlc.services/iiif-img/7/6/76e1ce36-7b6e-4451-8ab5-3eb72db90856/canvas/c/427#xywh=1784,3029,389,39"
        },
        {
            "id": "https://tu-delft-heritage.github.io/iiif-annotations/426/annotation/40",
            "type": "Annotation",
            "motivation": "supplementing",
            "body": {
                "type": "TextualBody",
                "format": "text/plain",
                "value": "HOOGLEERAAR"
            },
            "target": "https://dlc.services/iiif-img/7/6/76e1ce36-7b6e-4451-8ab5-3eb72db90856/canvas/c/427#xywh=1646,3089,241,22"
        },
        {
            "id": "https://tu-delft-heritage.github.io/iiif-annotations/426/annotation/41",
            "type": "Annotation",
            "motivation": "supplementing",
            "body": {
                "type": "TextualBody",
                "format": "text/plain",
                "value": "IN"
            },
            "target": "https://dlc.services/iiif-img/7/6/76e1ce36-7b6e-4451-8ab5-3eb72db90856/canvas/c/427#xywh=1909,3091,29,20"
        },
        {
            "id": "https://tu-delft-heritage.github.io/iiif-annotations/426/annotation/42",
            "type": "Annotation",
            "motivation": "supplementing",
            "body": {
                "type": "TextualBody",
                "format": "text/plain",
                "value": "DE"
            },
            "target": "https://dlc.services/iiif-img/7/6/76e1ce36-7b6e-4451-8ab5-3eb72db90856/canvas/c/427#xywh=1962,3091,40,21"
        },
        {
            "id": "https://tu-delft-heritage.github.io/iiif-annotations/426/annotation/43",
            "type": "Annotation",
            "motivation": "supplementing",
            "body": {
                "type": "TextualBody",
                "format": "text/plain",
                "value": "TOEG"
            },
            "target": "https://dlc.services/iiif-img/7/6/76e1ce36-7b6e-4451-8ab5-3eb72db90856/canvas/c/427#xywh=2025,3091,82,22"
        },
        {
            "id": "https://tu-delft-heritage.github.io/iiif-annotations/426/annotation/44",
            "type": "Annotation",
            "motivation": "supplementing",
            "body": {
                "type": "TextualBody",
                "format": "text/plain",
                "value": "WISKUNDE"
            },
            "target": "https://dlc.services/iiif-img/7/6/76e1ce36-7b6e-4451-8ab5-3eb72db90856/canvas/c/427#xywh=1646,3125,164,21"
        },
        {
            "id": "https://tu-delft-heritage.github.io/iiif-annotations/426/annotation/45",
            "type": "Annotation",
            "motivation": "supplementing",
            "body": {
                "type": "TextualBody",
                "format": "text/plain",
                "value": "EN"
            },
            "target": "https://dlc.services/iiif-img/7/6/76e1ce36-7b6e-4451-8ab5-3eb72db90856/canvas/c/427#xywh=1834,3126,40,21"
        },
        {
            "id": "https://tu-delft-heritage.github.io/iiif-annotations/426/annotation/46",
            "type": "Annotation",
            "motivation": "supplementing",
            "body": {
                "type": "TextualBody",
                "format": "text/plain",
                "value": "MECHANICA."
            },
            "target": "https://dlc.services/iiif-img/7/6/76e1ce36-7b6e-4451-8ab5-3eb72db90856/canvas/c/427#xywh=1897,3127,195,22"
        },
        {
            "id": "https://tu-delft-heritage.github.io/iiif-annotations/426/annotation/47",
            "type": "Annotation",
            "motivation": "supplementing",
            "body": {
                "type": "TextualBody",
                "format": "text/plain",
                "value": "HOOGLEERAAR"
            },
            "target": "https://dlc.services/iiif-img/7/6/76e1ce36-7b6e-4451-8ab5-3eb72db90856/canvas/c/427#xywh=554,1677,244,22"
        },
        {
            "id": "https://tu-delft-heritage.github.io/iiif-annotations/426/annotation/48",
            "type": "Annotation",
            "motivation": "supplementing",
            "body": {
                "type": "TextualBody",
                "format": "text/plain",
                "value": "IN"
            },
            "target": "https://dlc.services/iiif-img/7/6/76e1ce36-7b6e-4451-8ab5-3eb72db90856/canvas/c/427#xywh=819,1679,30,20"
        },
        {
            "id": "https://tu-delft-heritage.github.io/iiif-annotations/426/annotation/49",
            "type": "Annotation",
            "motivation": "supplementing",
            "body": {
                "type": "TextualBody",
                "format": "text/plain",
                "value": "HET"
            },
            "target": "https://dlc.services/iiif-img/7/6/76e1ce36-7b6e-4451-8ab5-3eb72db90856/canvas/c/427#xywh=872,1679,61,21"
        },
        {
            "id": "https://tu-delft-heritage.github.io/iiif-annotations/426/annotation/50",
            "type": "Annotation",
            "motivation": "supplementing",
            "body": {
                "type": "TextualBody",
                "format": "text/plain",
                "value": "BOETSEEREN"
            },
            "target": "https://dlc.services/iiif-img/7/6/76e1ce36-7b6e-4451-8ab5-3eb72db90856/canvas/c/427#xywh=957,1679,214,24"
        },
        {
            "id": "https://tu-delft-heritage.github.io/iiif-annotations/426/annotation/51",
            "type": "Annotation",
            "motivation": "supplementing",
            "body": {
                "type": "TextualBody",
                "format": "text/plain",
                "value": "EN"
            },
            "target": "https://dlc.services/iiif-img/7/6/76e1ce36-7b6e-4451-8ab5-3eb72db90856/canvas/c/427#xywh=552,1712,43,21"
        },
        {
            "id": "https://tu-delft-heritage.github.io/iiif-annotations/426/annotation/52",
            "type": "Annotation",
            "motivation": "supplementing",
            "body": {
                "type": "TextualBody",
                "format": "text/plain",
                "value": "DE"
            },
            "target": "https://dlc.services/iiif-img/7/6/76e1ce36-7b6e-4451-8ab5-3eb72db90856/canvas/c/427#xywh=618,1712,40,22"
        },
        {
            "id": "https://tu-delft-heritage.github.io/iiif-annotations/426/annotation/53",
            "type": "Annotation",
            "motivation": "supplementing",
            "body": {
                "type": "TextualBody",
                "format": "text/plain",
                "value": "BEELDHOUWKUNST."
            },
            "target": "https://dlc.services/iiif-img/7/6/76e1ce36-7b6e-4451-8ab5-3eb72db90856/canvas/c/427#xywh=681,1714,318,23"
        },
        {
            "id": "https://tu-delft-heritage.github.io/iiif-annotations/426/annotation/54",
            "type": "Annotation",
            "motivation": "supplementing",
            "body": {
                "type": "TextualBody",
                "format": "text/plain",
                "value": "H."
            },
            "target": "https://dlc.services/iiif-img/7/6/76e1ce36-7b6e-4451-8ab5-3eb72db90856/canvas/c/427#xywh=547,3016,44,35"
        },
        {
            "id": "https://tu-delft-heritage.github.io/iiif-annotations/426/annotation/55",
            "type": "Annotation",
            "motivation": "supplementing",
            "body": {
                "type": "TextualBody",
                "format": "text/plain",
                "value": "A."
            },
            "target": "https://dlc.services/iiif-img/7/6/76e1ce36-7b6e-4451-8ab5-3eb72db90856/canvas/c/427#xywh=617,3017,44,35"
        },
        {
            "id": "https://tu-delft-heritage.github.io/iiif-annotations/426/annotation/56",
            "type": "Annotation",
            "motivation": "supplementing",
            "body": {
                "type": "TextualBody",
                "format": "text/plain",
                "value": "RAVENEK,"
            },
            "target": "https://dlc.services/iiif-img/7/6/76e1ce36-7b6e-4451-8ab5-3eb72db90856/canvas/c/427#xywh=687,3017,269,44"
        },
        {
            "id": "https://tu-delft-heritage.github.io/iiif-annotations/426/annotation/57",
            "type": "Annotation",
            "motivation": "supplementing",
            "body": {
                "type": "TextualBody",
                "format": "text/plain",
                "value": "W.l."
            },
            "target": "https://dlc.services/iiif-img/7/6/76e1ce36-7b6e-4451-8ab5-3eb72db90856/canvas/c/427#xywh=982,3021,88,36"
        },
        {
            "id": "https://tu-delft-heritage.github.io/iiif-annotations/426/annotation/58",
            "type": "Annotation",
            "motivation": "supplementing",
            "body": {
                "type": "TextualBody",
                "format": "text/plain",
                "value": "HOOGLEERAAR"
            },
            "target": "https://dlc.services/iiif-img/7/6/76e1ce36-7b6e-4451-8ab5-3eb72db90856/canvas/c/427#xywh=546,3076,244,23"
        },
        {
            "id": "https://tu-delft-heritage.github.io/iiif-annotations/426/annotation/59",
            "type": "Annotation",
            "motivation": "supplementing",
            "body": {
                "type": "TextualBody",
                "format": "text/plain",
                "value": "IN"
            },
            "target": "https://dlc.services/iiif-img/7/6/76e1ce36-7b6e-4451-8ab5-3eb72db90856/canvas/c/427#xywh=811,3079,30,21"
        },
        {
            "id": "https://tu-delft-heritage.github.io/iiif-annotations/426/annotation/60",
            "type": "Annotation",
            "motivation": "supplementing",
            "body": {
                "type": "TextualBody",
                "format": "text/plain",
                "value": "DE"
            },
            "target": "https://dlc.services/iiif-img/7/6/76e1ce36-7b6e-4451-8ab5-3eb72db90856/canvas/c/427#xywh=864,3080,41,21"
        },
        {
            "id": "https://tu-delft-heritage.github.io/iiif-annotations/426/annotation/61",
            "type": "Annotation",
            "motivation": "supplementing",
            "body": {
                "type": "TextualBody",
                "format": "text/plain",
                "value": "A."
            },
            "target": "https://dlc.services/iiif-img/7/6/76e1ce36-7b6e-4451-8ab5-3eb72db90856/canvas/c/427#xywh=556,1614,44,38"
        },
        {
            "id": "https://tu-delft-heritage.github.io/iiif-annotations/426/annotation/62",
            "type": "Annotation",
            "motivation": "supplementing",
            "body": {
                "type": "TextualBody",
                "format": "text/plain",
                "value": "W."
            },
            "target": "https://dlc.services/iiif-img/7/6/76e1ce36-7b6e-4451-8ab5-3eb72db90856/canvas/c/427#xywh=625,1618,53,35"
        },
        {
            "id": "https://tu-delft-heritage.github.io/iiif-annotations/426/annotation/63",
            "type": "Annotation",
            "motivation": "supplementing",
            "body": {
                "type": "TextualBody",
                "format": "text/plain",
                "value": "M."
            },
            "target": "https://dlc.services/iiif-img/7/6/76e1ce36-7b6e-4451-8ab5-3eb72db90856/canvas/c/427#xywh=703,1618,54,36"
        },
        {
            "id": "https://tu-delft-heritage.github.io/iiif-annotations/426/annotation/64",
            "type": "Annotation",
            "motivation": "supplementing",
            "body": {
                "type": "TextualBody",
                "format": "text/plain",
                "value": "ODE"
            },
            "target": "https://dlc.services/iiif-img/7/6/76e1ce36-7b6e-4451-8ab5-3eb72db90856/canvas/c/427#xywh=783,1614,111,41"
        },
        {
            "id": "https://tu-delft-heritage.github.io/iiif-annotations/426/annotation/65",
            "type": "Annotation",
            "motivation": "supplementing",
            "body": {
                "type": "TextualBody",
                "format": "text/plain",
                "value": "Jr."
            },
            "target": "https://dlc.services/iiif-img/7/6/76e1ce36-7b6e-4451-8ab5-3eb72db90856/canvas/c/427#xywh=920,1619,66,40"
        },
        {
            "id": "https://tu-delft-heritage.github.io/iiif-annotations/426/annotation/66",
            "type": "Annotation",
            "motivation": "supplementing",
            "body": {
                "type": "TextualBody",
                "format": "text/plain",
                "value": "WERKTUIGBOUWKUNDE,"
            },
            "target": "https://dlc.services/iiif-img/7/6/76e1ce36-7b6e-4451-8ab5-3eb72db90856/canvas/c/427#xywh=546,3111,383,26"
        }
    ]
}